syllabus/__init__.py
syllabus/argv.py
syllabus/basic.py
syllabus/interactive.py
syllabus/task.py
syllabus/tests.py
syllabus/viewer.py
syllabus/app_utils/__init__.py
syllabus/app_utils/blocks.py
syllabus/app_utils/getch.py
syllabus/format/__init__.py
syllabus/format/units.py
syllabus/format/utils.py
syllabus/parallel/__init__.py
syllabus/parallel/parallel_mixins.py
syllabus/parallel/threadpool.py
syllabus/reporting/__init__.py
syllabus/reporting/accountant.py
syllabus/reporting/order.py
syllabus/reporting/reporter_mixins.py
syllabus/reporting/tests.py
Syllabus-2.0.dist-info/LICENSE
Syllabus-2.0.dist-info/METADATA
Syllabus-2.0.dist-info/WHEEL
Syllabus-2.0.dist-info/top_level.txt
Syllabus-2.0.dist-info/RECORD
