Metadata-Version: 2.1
Name: Syllabus
Version: 2.0
Summary: Time and memory tracking task manager for Machine Learning applications
Home-page: https://github.com/thetianshuhuang/syllabus
Author: Tianshu Huang
Author-email: thetianshuhuang@gmail.com
License: MIT
Platform: UNKNOWN
Classifier: Programming Language :: Python :: 3
Classifier: License :: OSI Approved :: MIT License
Classifier: Operating System :: OS Independent
Requires-Dist: printtools
Requires-Dist: ansiwrap
